data_diff/__init__.py
data_diff/__main__.py
data_diff/abcs/__init__.py
data_diff/abcs/compiler.py
data_diff/abcs/database_types.py
data_diff/config.py
data_diff/databases/__init__.py
data_diff/databases/_connect.py
data_diff/databases/base.py
data_diff/databases/bigquery.py
data_diff/databases/clickhouse.py
data_diff/databases/databricks.py
data_diff/databases/duckdb.py
data_diff/databases/mssql.py
data_diff/databases/mysql.py
data_diff/databases/oracle.py
data_diff/databases/postgresql.py
data_diff/databases/presto.py
data_diff/databases/redshift.py
data_diff/databases/snowflake.py
data_diff/databases/trino.py
data_diff/databases/vertica.py
data_diff/diff_tables.py
data_diff/errors.py
data_diff/format.py
data_diff/hashdiff_tables.py
data_diff/info_tree.py
data_diff/joindiff_tables.py
data_diff/lexicographic_space.py
data_diff/parse_time.py
data_diff/py.typed
data_diff/queries/__init__.py
data_diff/queries/api.py
data_diff/queries/ast_classes.py
data_diff/queries/base.py
data_diff/queries/extras.py
data_diff/query_utils.py
data_diff/schema.py
data_diff/table_segment.py
data_diff/thread_utils.py
data_diff/utils.py
data_diff/version.py
dcs_cli/__init__.py
dcs_cli/__main__.py
dcs_cli/__version__.py
dcs_cli/dcs/__init__.py
dcs_cli/dcs/cli.py
dcs_cli/dcs/data_differ.py
dcs_cli/dcs/main.py
dcs_cli/dcs/models/data_diff_models.py
dcs_cli/dcs/serializer.py
dcs_cli/dcs/table.py
dcs_cli/dcs/themes.py
dcs_cli/dcs/utils.py
dcs_cli-0.3.113.dist-info/METADATA
dcs_cli-0.3.113.dist-info/WHEEL
dcs_cli-0.3.113.dist-info/entry_points.txt
dcs_cli-0.3.113.dist-info/RECORD
